mkdocs_include_dir_to_nav/__init__.py
mkdocs_include_dir_to_nav/include_dir_to_nav.py
mkdocs_include_dir_to_nav-1.2.0.dist-info/METADATA
mkdocs_include_dir_to_nav-1.2.0.dist-info/WHEEL
mkdocs_include_dir_to_nav-1.2.0.dist-info/entry_points.txt
mkdocs_include_dir_to_nav-1.2.0.dist-info/top_level.txt
mkdocs_include_dir_to_nav-1.2.0.dist-info/RECORD
