Metadata-Version: 2.1
Name: mkdocs-include-dir-to-nav
Version: 1.2.0
Summary: A MkDocs plugin include all file in dir to navigation
Home-page: https://github.com/mysiki/mkdocs_include_dir_to_nav
Author: mysiki
License: MIT
Keywords: mkdocs,navigation,plugin,directory,folder
Platform: UNKNOWN
Requires-Python: >=3.6
Requires-Dist: mkdocs (>=1.0.4)
